CONTRIBUTORS
LICENSE
pyproject.toml
pyrhhfbp/__init__.py
pyrhhfbp/cache.py
pyrhhfbp/exceptions.py
pyrhhfbp/models/__init__.py
pyrhhfbp/models/base.py
pyrhhfbp/models/instrument.py
pyrhhfbp/models/oauth.py
pyrhhfbp/models/portfolio.py
pyrhhfbp/models/sessionmanager.py
pyrhhfbp/robinhood.py
pyrhhfbp/test_login_smsauth.py
pyrhhfbp/trade_history_downloader.py
pyrhhfbp/urls.py
pyrhhfbp-2.0.2rc0.dist-info/LICENSE
pyrhhfbp-2.0.2rc0.dist-info/WHEEL
pyrhhfbp-2.0.2rc0.dist-info/METADATA
pyrhhfbp-2.0.2rc0.dist-info/RECORD
