Metadata-Version: 2.1
Name: pyrhhfbp
Version: 2.0.2rc0
Summary: Unofficial Robinhood Python API...forked by HenryFBP to update an outdated PyPI package
Home-page: https://github.com/georgianpartners/foreshadow
License: MIT
Keywords: trading,options,robinhood,stock,api
Author: Unofficial Robinhood Python API Developers
Requires-Python: >=3.6,<4.0
Classifier: License :: OSI Approved :: MIT License
Classifier: Programming Language :: Python :: 3
Classifier: Programming Language :: Python :: 3.10
Classifier: Programming Language :: Python :: 3.6
Classifier: Programming Language :: Python :: 3.7
Classifier: Programming Language :: Python :: 3.8
Classifier: Programming Language :: Python :: 3.9
Provides-Extra: docs
Provides-Extra: notebook
Requires-Dist: autodocsumm (>=0.1.13,<0.2.0); extra == "docs"
Requires-Dist: certifi (>=2020.4.5,<2021.0.0)
Requires-Dist: marshmallow (>=3.5.1,<4.0.0)
Requires-Dist: notebook (>=6.0.3,<7.0.0); extra == "notebook"
Requires-Dist: python-dateutil (>=2.8,<3.0)
Requires-Dist: python-dotenv (>=0.13.0,<0.14.0); extra == "notebook"
Requires-Dist: pytz (>=2019.3,<2020.0)
Requires-Dist: requests (>=2.23,<3.0)
Requires-Dist: sphinx (>=2.4.4,<3.0.0); extra == "docs"
Requires-Dist: sphinx-autodoc-typehints (>=1.10.3,<2.0.0); extra == "docs"
Requires-Dist: sphinx_rtd_theme (>=0.4.3,<0.5.0); extra == "docs"
Requires-Dist: yarl (>=1.4.2,<2.0.0)
Project-URL: Repository, https://github.com/georgianpartners/foreshadow
